{"cameraMode":{"drawMode":0,"name":"Shaded","section":"Shading Mode"},"sceneLighting":true,"audioPlay":false,"sceneViewState":{"showFog":true,"showMaterialUpdate":false,"showSkybox":true,"showFlares":true,"showImageEffects":true,"showParticleSystems":true},"in2DMode":false,"pivot":{"x":75.8665771484375,"y":121.19876098632813,"z":-155.31048583984376},"rotation":{"x":-0.032389841973781589,"y":0.9658827781677246,"z":-0.14895065128803254,"w":-0.21005503833293916},"size":1018.6492919921875,"orthographic":false}